wifi_heat_mapper/__init__.py
wifi_heat_mapper/_version.py
wifi_heat_mapper/config.py
wifi_heat_mapper/debugger.py
wifi_heat_mapper/graph.py
wifi_heat_mapper/gui.py
wifi_heat_mapper/main.py
wifi_heat_mapper/misc.py
whm-0.2.4.dist-info/LICENSE
whm-0.2.4.dist-info/METADATA
whm-0.2.4.dist-info/WHEEL
whm-0.2.4.dist-info/entry_points.txt
whm-0.2.4.dist-info/top_level.txt
whm-0.2.4.dist-info/zip-safe
whm-0.2.4.dist-info/RECORD
