Metadata-Version: 2.1
Name: whm
Version: 0.2.4
Summary: A Python application for generating WiFi heatmaps with various parameters
Home-page: https://github.com/Nischay-Pro/wifi-heat-mapper
Author: Nischay Mamidi
Author-email: NischayPro@protonmail.com
License: UNKNOWN
Project-URL: Bug Tracker, https://github.com/Nischay-Pro/wifi-heat-mapper/issues
Platform: UNKNOWN
Classifier: Programming Language :: Python :: 3
Classifier: License :: OSI Approved :: GNU General Public License v3 or later (GPLv3+)
Classifier: Operating System :: POSIX :: Linux
Requires-Python: >=3.7
